canml/__init__.py
canml/canmlio.py
canml-0.1.14.dist-info/licenses/LICENSE
canml-0.1.14.dist-info/METADATA
canml-0.1.14.dist-info/WHEEL
canml-0.1.14.dist-info/top_level.txt
canml-0.1.14.dist-info/RECORD
