Metadata-Version: 2.4
Name: canml
Version: 0.1.14
Summary: Decode CAN BLF logs using DBC files into pandas DataFrames and export to CSV
Author-email: "Cosmin B. Memetea" <cosmin.memetea@gmail.com>
License: MIT
Project-URL: Homepage, https://github.com/cosminmemetea/canml
Project-URL: Documentation, https://canml.readthedocs.io/
Project-URL: Source, https://github.com/cosminmemetea/canml
Project-URL: Tracker, https://github.com/cosminmemetea/canml/issues
Classifier: Development Status :: 4 - Beta
Classifier: Intended Audience :: Developers
Classifier: License :: OSI Approved :: MIT License
Classifier: Programming Language :: Python :: 3
Classifier: Programming Language :: Python :: 3.8
Classifier: Topic :: Scientific/Engineering :: Information Analysis
Requires-Python: >=3.8
License-File: LICENSE
Requires-Dist: cantools==39.4.4
Requires-Dist: python-can==4.4.0
Requires-Dist: pandas==2.2.2
Requires-Dist: numpy==1.26.4
Requires-Dist: tqdm>=4.0.0
Requires-Dist: pyarrow>=11.0.0
Provides-Extra: test
Requires-Dist: pytest>=7.0.0; extra == "test"
Requires-Dist: coverage; extra == "test"
Requires-Dist: codecov; extra == "test"
Requires-Dist: twine; extra == "test"
Requires-Dist: build; extra == "test"
Dynamic: license-file
